{
  "dna_hash": "bcde645b6a63fbbf",
  "generation": 1,
  "age_days": 0,
  "mutation_count": 123,
  "rarity_score": 31.666666666666664,
  "parent_id": null,
  "traits": {
    "body_color": {
      "value": "pink",
      "rarity": "rare"
    },
    "face_expression": {
      "value": "neutral",
      "rarity": "common"
    },
    "accessory": {
      "value": "none",
      "rarity": "common"
    },
    "pattern": {
      "value": "diamonds",
      "rarity": "uncommon"
    },
    "background": {
      "value": "aurora",
      "rarity": "rare"
    },
    "special": {
      "value": "energy",
      "rarity": "rare"
    }
  },
  "last_updated": "2026-07-11T03:28:50.827274"
}